Workbook

Sheet 00-COVER
GS8: Étude de faisabilité d'un Green Bond Programme photovoltaïque Ciments du Maroc : un Modèle financier 17 MW (Tafukt + Chems), avec un cAPEX de 119 MDH
M17: SUJET : Une Étude de faisabilité d'un Green Bond : Programme photovoltaïque Ciments du Maroc
M19: Projet : Modèle financier 17 MW (Tafukt + Chems), CAPEX 119 MDH
M21: Realise par : OUIDAD RAJAE

Sheet 01-ASSUMPTIONS
E6: Des hypotheses :
G7: Hypothese | H7: Valeur | I7: justification
G8: Puissance installe | H8: 17 MW | I8: Puissance total du programme : tafukt 10MW a ait baha + chems 7MW a SAFI (Rapport financier annuel 2024, ciments du maroc)
G9: Cout unitaire | H9: 7 DH/Wc | I9: Estimation dans la fourchette de marche inferieur a 10 DH/WC pour instalation photovoltaiques industrielles au maroc (FNH,article sur les energies renouvlables au maroc )
G10: CAPEX (total) | H10: 119 | I10: =17000000Wc *7Dh/Wc
G11: Rendement | H11: 1700MWh/MW/an | I11: la valeur medianne de la fourchette du rendement de projets solaires marocains comparables (Nexans mohammedia: 1571 et Noor tafilalet erfoud : 1800)
G12: Production annuelle | H12: 28900 MWH/an | I12: 1700MW*1700 (pour le programme tafukt et chems)
G13: Prix electricite | H13: 0,80 MAD/kWh | I13: Les gros consommateurs indus en haute tention leurs tarifs se situent dans partie basse de fourchette officielle 0,60-2 DH/kWh
G14: Economie annelle estimee | H14: 23.1 | I14: = 28900 * 0,8
G15: Coupon | H15: 0.04 | I15: Par analogie avec l'émission obligataire OCP de décembre 2024 (comparable industriel marocain) : son taux de référence dapres courbe BT est de 3,36% + prime de risque de (40-50 pbs).on a ajuste Prime à 75 pbs pour Ciments du Maroc car un émetteur privé, non quasi-souverain pas assez sur comme OCP
G16: Taux dIS | H16: 0.35 | I16: barème IS marocain 2026, grandes entreprises (bénéfice net ≥ 100 MDH)
G17: Coupon apres IS | H17: 0.026 | I17: 4,0% × (1-35%) = 2,6%
G18: Taux dactualisation | H18: 0.08 | I18: Proxy standard du WACC pour un projet industriel au Maroc,en l'absence de données internes précises (structure actionnariale, bêta..). Volontairement supérieur au coupon de la dette (4,0%) car il intègre l'exigence de rendement des actionnaires élevée a celle des créancier obligataires.
G19: OPEX = 1,5% du CAPEX | H19: 1.8 | I19: on a utilise un benchmark international (IRENA) courant pour l'O&M solaire industriel a cause dabscence de source marocaine spécifique
G20: Facteur d'émiss- ion | H20: 0,756 tCO2/MWh | I20: (donnée 2019, ecoactu.ma). Probablement légèrement surestimé car Le facteur d'émission réel en 2024-2025 est probablement plus bas que 0,756 grace a lengagement du maroc aux energies renouvlables
G21: CO₂ évité | H21: 21 848 tCO2/an | I21: 28 900 MWh/an × 0,756 tCO₂/MWh = 21 848 tonnes de CO₂ évitées par an

Sheet 02-FINANCIAL ANALYSIS
B6: Donnees consolidees en MMAD
F8: 2022 | G8: 2023 | H8: 2024
E9: CA (operationnel) | F9: 4043 | G9: 4305 | H9: 4364
E10: EBE (EBITDA) | F10: 1587 | G10: 1654 | H10: 1779
E11: Resultat dexploitation | F11: 1327 | G11: 1428 | H11: 1557
E12: Resultat NET | F12: 917 | G12: 994 | H12: 935
E13: CAF | F13: 1146 | G13: 1171 | H13: 1315
E14: Dette Financiere | F14: 0 | G14: 0 | H14: 0
E15: DETTE court terme | F15: 140 | G15: 187.7 | H15: 186.6
E16: TRESORIE | F16: 73.8 | G16: 88.3 | H16: 82
E17: Dette nette | F17: 66.2 | G17: 99.4 | H17: 104.6
E18: Capitaux propres | F18: 3193.4 | G18: 3308.9 | H18: 3197.8
E19: CAPEX historique | G19: 166.2 | H19: 191.9
E20: source : Rapports financiers annuels 2023 et 2024 ciments du maroc , cimentsdumaroc.com
B23: Calcul des ratios et interpretation
D24: 1- Marge EBITDA (EBE/CA)
F25: 2022 | G25: 2023 | H25: 2024
E26: Marge EBITDA | F26: =F10/F9 -> 0.3925303 | G26: =G10/G9 -> 0.38420441 | H26: =H10/H9 -> 0.40765353
D28: 2-Croissance du CA (2022-2024) | F28: (CA du N-2 -CA du N)/CA du N= | I28: =(H9-F9)/H9 -> 0.07355637
D31: 3 -Dettes / EBITDA
E32: Avant emission du green bond : Ratio = 104,6/ 1779 = 0,059x
E33: Avant emission du green bond : Ratio =(104,6+119) = 0,126x

Sheet 03-CASH FLOW
E2: Calcul du cash flow :
G3: Année 2025 | H3: Année 2026 | I3: Année 2027 | J3: Année 2028 | K3: Année 2029 | L3: Année 2030 | M3: Année 2031
F4: Economie delectricite | G4: ='01-ASSUMPTIONS'!$H$14 -> 23.1 | H4: ='01-ASSUMPTIONS'!$H$14 -> 23.1 | I4: ='01-ASSUMPTIONS'!$H$14 -> 23.1 | J4: ='01-ASSUMPTIONS'!$H$14 -> 23.1 | K4: ='01-ASSUMPTIONS'!$H$14 -> 23.1 | L4: ='01-ASSUMPTIONS'!$H$14 -> 23.1 | M4: ='01-ASSUMPTIONS'!$H$14 -> 23.1
F5: OPEX (maintenance) | G5: =-'01-ASSUMPTIONS'!$H$19 -> -1.8 | H5: =-'01-ASSUMPTIONS'!$H$19 -> -1.8 | I5: =-'01-ASSUMPTIONS'!$H$19 -> -1.8 | J5: =-'01-ASSUMPTIONS'!$H$19 -> -1.8 | K5: =-'01-ASSUMPTIONS'!$H$19 -> -1.8 | L5: =-'01-ASSUMPTIONS'!$H$19 -> -1.8 | M5: =-'01-ASSUMPTIONS'!$H$19 -> -1.8
F6: Cash-flow net avant dette | G6: =$G$4+$G$5 -> 21.3 | H6: =$G$4+$G$5 -> 21.3 | I6: =$G$4+$G$5 -> 21.3 | J6: =$G$4+$G$5 -> 21.3 | K6: =$G$4+$G$5 -> 21.3 | L6: =$G$4+$G$5 -> 21.3 | M6: =$G$4+$G$5 -> 21.3
F7: Intérêts Green Bond | G7: =-'01-ASSUMPTIONS'!$H$15*'01-ASSUMPTIONS'!$H$10 -> -4.76 | H7: =-'01-ASSUMPTIONS'!$H$15*'01-ASSUMPTIONS'!$H$10 -> -4.76 | I7: =-'01-ASSUMPTIONS'!$H$15*'01-ASSUMPTIONS'!$H$10 -> -4.76 | J7: =-'01-ASSUMPTIONS'!$H$15*'01-ASSUMPTIONS'!$H$10 -> -4.76 | K7: =-'01-ASSUMPTIONS'!$H$15*'01-ASSUMPTIONS'!$H$10 -> -4.76 | L7: =-'01-ASSUMPTIONS'!$H$15*'01-ASSUMPTIONS'!$H$10 -> -4.76 | M7: =-'01-ASSUMPTIONS'!$H$15*'01-ASSUMPTIONS'!$H$10 -> -4.76
F8: Economie impot sur interet | G8: =-G7*'01-ASSUMPTIONS'!$H$16 -> 1.666 | H8: =-H7*'01-ASSUMPTIONS'!$H$16 -> 1.666 | I8: =-I7*'01-ASSUMPTIONS'!$H$16 -> 1.666 | J8: =-J7*'01-ASSUMPTIONS'!$H$16 -> 1.666 | K8: =-K7*'01-ASSUMPTIONS'!$H$16 -> 1.666 | L8: =-L7*'01-ASSUMPTIONS'!$H$16 -> 1.666 | M8: =-M7*'01-ASSUMPTIONS'!$H$16 -> 1.666
F9: Cash-flow net après dette | G9: =G6+G7 -> 16.54 | H9: =H6+H7 -> 16.54 | I9: =I6+I7 -> 16.54 | J9: =J6+J7 -> 16.54 | K9: =K6+K7 -> 16.54 | L9: =L6+L7 -> 16.54 | M9: =M6+M7 -> 16.54
F10: Cash-flow net apres dette et impot | G10: =G9+G8 -> 18.206 | H10: =H9+H8 -> 18.206 | I10: =I9+I8 -> 18.206 | J10: =J9+J8 -> 18.206 | K10: =K9+K8 -> 18.206 | L10: =L9+L8 -> 18.206 | M10: =M9+M8 -> 18.206
F11: Remboursement capital | G11: 0 | H11: 0 | I11: 0 | J11: 0 | K11: 0 | L11: 0 | M11: =-'01-ASSUMPTIONS'!H10 -> -119
F12: Cash cumulé | G12: =G10 -> 18.206 | H12: =G10+G12 -> 36.412 | I12: =H10+H12 -> 54.618 | J12: =I10+I12 -> 72.824 | K12: =J10+J12 -> 91.03 | L12: =K10+K12 -> 109.236 | M12: =L10+L12 -> 127.442
F13: Test de capacité de remboursement du Green Bond flux annuels 2025-2031

Sheet 04-VALUATION
F5: Calcul de la VAN et le TRI :
G7: annee 1 | H7: annee 2 | I7: annee 3 | J7: annee 4 | K7: annee 5 | L7: annee 6 | M7: annee 7 | N7: annee 8 | O7: annee 9 | P7: annee 10 | Q7: annee 11 | R7: annee 12 | S7: annee 13 | T7: annee 14 | U7: annee 15 | V7: annee 16 | W7: annee 17 | X7: annee 18 | Y7: annee 19 | Z7: annee 20
F8: Cash flow Net | G8: ='01-ASSUMPTIONS'!$H$14-'01-ASSUMPTIONS'!$H$19 -> 21.3 | H8: ='01-ASSUMPTIONS'!$H$14-'01-ASSUMPTIONS'!$H$19 -> 21.3 | I8: ='01-ASSUMPTIONS'!$H$14-'01-ASSUMPTIONS'!$H$19 -> 21.3 | J8: ='01-ASSUMPTIONS'!$H$14-'01-ASSUMPTIONS'!$H$19 -> 21.3 | K8: ='01-ASSUMPTIONS'!$H$14-'01-ASSUMPTIONS'!$H$19 -> 21.3 | L8: ='01-ASSUMPTIONS'!$H$14-'01-ASSUMPTIONS'!$H$19 -> 21.3 | M8: ='01-ASSUMPTIONS'!$H$14-'01-ASSUMPTIONS'!$H$19 -> 21.3 | N8: ='01-ASSUMPTIONS'!$H$14-'01-ASSUMPTIONS'!$H$19 -> 21.3 | ... Z8: ='01-ASSUMPTIONS'!$H$14-'01-ASSUMPTIONS'!$H$19 -> 21.3
F9: =G13 -> -119 | G9: =G8 -> 21.3 | H9: =H8 -> 21.3 | I9: =I8 -> 21.3 | J9: =J8 -> 21.3 | K9: =K8 -> 21.3 | L9: =L8 -> 21.3 | M9: =M8 -> 21.3 | N9: =N8 -> 21.3 | ... Z9: =Z8 -> 21.3
G12: Annee 0 | M12: VAN | N12: TRI
F13: CAPEX | G13: =-'01-ASSUMPTIONS'!H10 -> -119 | M13: =NPV('01-ASSUMPTIONS'!$H$18,'04-VALUATION'!G8:Z8)+'04-VALUATION'!G13 -> 90.12654 | N13: =IRR(F9:Z9) -> 0.17143215

Sheet 05-SCENARIOS
H5: 1 - Changement de la VAN et le TRI selon differents scenarios :
K7: Rendement | L7: Prix elec | M7: Economie annuelle | O7: Van | P7: TRI
J8: Pessimiste | K8: 1400 | L8: 0.56 | M8: 15.3 | O8: =-'01-ASSUMPTIONS'!$H$10+('05-SCENARIOS'!M8-'01-ASSUMPTIONS'!$H$19)*(1-(1+'01-ASSUMPTIONS'!$H$18)^-20)/'01-ASSUMPTIONS'!$H$18 -> 13.54499 | P8: =RATE(20,M8-'01-ASSUMPTIONS'!$H$19,-'01-ASSUMPTIONS'!$H$10) -> 0.094960425
J9: Central | K9: 1700 | L9: 0.8 | M9: 23.1 | O9: =-'01-ASSUMPTIONS'!$H$10+('05-SCENARIOS'!M9-'01-ASSUMPTIONS'!$H$19)*(1-(1+'01-ASSUMPTIONS'!$H$18)^-20)/'01-ASSUMPTIONS'!$H$18 -> 90.12654 | P9: =RATE(20,M9-'01-ASSUMPTIONS'!$H$19,-'01-ASSUMPTIONS'!$H$10) -> 0.17143215
J10: Optimiste | K10: 1900 | L10: 0.9 | M10: 29.1 | O10: =-'01-ASSUMPTIONS'!$H$10+('05-SCENARIOS'!M10-'01-ASSUMPTIONS'!$H$19)*(1-(1+'01-ASSUMPTIONS'!$H$18)^-20)/'01-ASSUMPTIONS'!$H$18 -> 149.03542 | P10: =IRR(F16:Z16) -> 0.22548093
F16: =-'01-ASSUMPTIONS'!$H$10 -> -119 | G16: =$M$10-'01-ASSUMPTIONS'!$H$19 -> 27.3 | H16: =$M$10-'01-ASSUMPTIONS'!$H$19 -> 27.3 | I16: =$M$10-'01-ASSUMPTIONS'!$H$19 -> 27.3 | J16: =$M$10-'01-ASSUMPTIONS'!$H$19 -> 27.3 | K16: =$M$10-'01-ASSUMPTIONS'!$H$19 -> 27.3 | L16: =$M$10-'01-ASSUMPTIONS'!$H$19 -> 27.3 | M16: =$M$10-'01-ASSUMPTIONS'!$H$19 -> 27.3 | N16: =$M$10-'01-ASSUMPTIONS'!$H$19 -> 27.3 | ... Z16: =$M$10-'01-ASSUMPTIONS'!$H$19 -> 27.3
